setup.py
Fuzzython.egg-info/PKG-INFO
Fuzzython.egg-info/SOURCES.txt
Fuzzython.egg-info/dependency_links.txt
Fuzzython.egg-info/top_level.txt
fsets/__init__.py
fsets/fuzzy_set.py
fsets/gamma.py
fsets/gaussian.py
fsets/pifunction.py
fsets/polygon.py
fsets/polynomial.py
fsets/sfunction.py
fsets/singleton.py
fsets/trapezoid.py
fsets/triangular.py
fsets/zfunction.py
norms/__init__.py
norms/max1.py
norms/norms.py
operators/__init__.py
operators/_and.py
operators/_not.py
operators/_or.py
operators/binary.py
operators/operator.py
operators/parser.py
operators/unary.py
rules/__init__.py
rules/mrule.py
rules/parser.py
rules/rule.py
rules/srule.py
rules/trule.py
store/FCLLexer.py
store/FCLParser.py
store/__init__.py
store/reader.py
systems/__init__.py
systems/mamdani.py
systems/sugeno.py
systems/system.py
systems/tsukamoto.py