Metadata-Version: 1.0
Name: Fuzzython
Version: 0.1.0
Summary: Fuzzy Logic and Fuzzy Inference Python 3 Library
Home-page: https://github.com/yudivian/fuzzython
Author: Medialab-UH
Author-email: yudy@uh.cu
License: LICENSE.txt
Keywords: Fuzzy Logic Library
Platform: UNKNOWN
